MANIFEST.in
README.md
setup.cfg
setup.py
cowcerts_certificate_render/__init__.py
cowcerts_certificate_render/__main__.py
cowcerts_certificate_render.egg-info/PKG-INFO
cowcerts_certificate_render.egg-info/SOURCES.txt
cowcerts_certificate_render.egg-info/dependency_links.txt
cowcerts_certificate_render.egg-info/entry_points.txt
cowcerts_certificate_render.egg-info/requires.txt
cowcerts_certificate_render.egg-info/top_level.txt
cowcerts_certificate_render/data/certificates/cowcerts-edu-20190403.json
cowcerts_certificate_render/data/certificates/cowcerts-edu-20190417.json
cowcerts_certificate_render/data/certificates/cowcerts-edu-20190422.json
cowcerts_certificate_render/data/templates/cowcerts-eds.html
cowcerts_certificate_render/data/templates/cowcerts-for-education.html