Metadata-Version: 2.1
Name: cowcerts-certificate-render
Version: 0.0.9
Summary: HTML template render for Cowcerts certificates visualization
Home-page: https://gitlab.com/btcalabs/certificate-render
Author: BTCA Labs
Author-email: btcalabs+cowcerts+certificate-render@btcassessors.com
License: UNKNOWN
Project-URL: Bug Reports, https://gitlab.com/btcalabs/certificate-render/issues
Project-URL: Source, https://gitlab.com/btcalabs/certificate-render
Keywords: cowcerts certificate template html render
Platform: UNKNOWN
Classifier: Development Status :: 3 - Alpha
Classifier: Intended Audience :: Developers
Classifier: Topic :: Software Development :: Build Tools
Classifier: Programming Language :: Python :: 3
Classifier: Programming Language :: Python :: 3.4
Classifier: Programming Language :: Python :: 3.5
Classifier: Programming Language :: Python :: 3.6
Classifier: Programming Language :: Python :: 3.7
